{
	"configurations" : 
	[
		{
			"directories" : 
			[
				{
					"build" : ".",
					"childIndexes" : 
					[
						1,
						2
					],
					"minimumCMakeVersion" : 
					{
						"string" : "3.8"
					},
					"projectIndex" : 0,
					"source" : "."
				},
				{
					"build" : "src",
					"minimumCMakeVersion" : 
					{
						"string" : "3.8"
					},
					"parentIndex" : 0,
					"projectIndex" : 0,
					"source" : "src",
					"targetIndexes" : 
					[
						0
					]
				},
				{
					"build" : "tests",
					"minimumCMakeVersion" : 
					{
						"string" : "3.8"
					},
					"parentIndex" : 0,
					"projectIndex" : 0,
					"source" : "tests",
					"targetIndexes" : 
					[
						1
					]
				}
			],
			"name" : "Debug",
			"projects" : 
			[
				{
					"directoryIndexes" : 
					[
						0,
						1,
						2
					],
					"name" : "blackjack",
					"targetIndexes" : 
					[
						0,
						1
					]
				}
			],
			"targets" : 
			[
				{
					"directoryIndex" : 1,
					"id" : "judge::@145eef247bfb46b6828c",
					"jsonFile" : "target-judge-Debug-05c4e02238da45391dff.json",
					"name" : "judge",
					"projectIndex" : 0
				},
				{
					"directoryIndex" : 2,
					"id" : "judge_test.out::@a44f0ac069e85531cdee",
					"jsonFile" : "target-judge_test.out-Debug-ea823df0e4128cf26557.json",
					"name" : "judge_test.out",
					"projectIndex" : 0
				}
			]
		}
	],
	"kind" : "codemodel",
	"paths" : 
	{
		"build" : "/media/sf_share/blackjack/build",
		"source" : "/media/sf_share/blackjack"
	},
	"version" : 
	{
		"major" : 2,
		"minor" : 0
	}
}
